picomidi/__init__.py
picomidi/aftertouch.py
picomidi/channel.py
picomidi/constant.py
picomidi/misc.py
picomidi/note.py
picomidi/song.py
picomidi/tempo.py
picomidi/value.py
picomidi/values.py
picomidi-0.1.0.dist-info/licenses/LICENSE
picomidi-0.1.0.dist-info/METADATA
picomidi-0.1.0.dist-info/WHEEL
picomidi-0.1.0.dist-info/top_level.txt
picomidi-0.1.0.dist-info/RECORD
