Metadata-Version: 2.4
Name: picomidi
Version: 0.1.0
Summary: A lightweight, focused MIDI library for Python
Home-page: https://github.com/yourusername/picomidi
Author: Mark Brooks
Author-email: 
License: MIT
Project-URL: Homepage, https://github.com/yourusername/picomidi
Project-URL: Documentation, https://github.com/yourusername/picomidi#readme
Project-URL: Repository, https://github.com/yourusername/picomidi
Project-URL: Issues, https://github.com/yourusername/picomidi/issues
Keywords: midi,music,audio,protocol,parser
Classifier: Development Status :: 4 - Beta
Classifier: Intended Audience :: Developers
Classifier: Topic :: Multimedia :: Sound/Audio :: MIDI
Classifier: License :: OSI Approved :: MIT License
Classifier: Programming Language :: Python :: 3
Classifier: Programming Language :: Python :: 3.8
Classifier: Programming Language :: Python :: 3.9
Classifier: Programming Language :: Python :: 3.10
Classifier: Programming Language :: Python :: 3.11
Classifier: Programming Language :: Python :: 3.12
Classifier: Operating System :: OS Independent
Requires-Python: >=3.8
License-File: LICENSE
Provides-Extra: dev
Requires-Dist: pytest>=7.0.0; extra == "dev"
Requires-Dist: pytest-cov>=4.0.0; extra == "dev"
Requires-Dist: black>=23.0.0; extra == "dev"
Requires-Dist: flake8>=6.0.0; extra == "dev"
Requires-Dist: mypy>=1.0.0; extra == "dev"
Dynamic: home-page
Dynamic: license-file
Dynamic: requires-python
